odoo/addons/product_variant_specific_tax/README.rst
odoo/addons/product_variant_specific_tax/__init__.py
odoo/addons/product_variant_specific_tax/__manifest__.py
odoo/addons/product_variant_specific_tax/i18n/product_variant_specific_tax.pot
odoo/addons/product_variant_specific_tax/models/__init__.py
odoo/addons/product_variant_specific_tax/models/product.py
odoo/addons/product_variant_specific_tax/models/sale_order_line.py
odoo/addons/product_variant_specific_tax/readme/CONTRIBUTORS.rst
odoo/addons/product_variant_specific_tax/readme/DESCRIPTION.rst
odoo/addons/product_variant_specific_tax/static/description/icon.png
odoo/addons/product_variant_specific_tax/static/description/index.html
odoo/addons/product_variant_specific_tax/tests/__init__.py
odoo/addons/product_variant_specific_tax/tests/test_sale_order.py
odoo/addons/product_variant_specific_tax/views/product_view.xml
odoo11_addon_product_variant_specific_tax-11.0.1.0.0.99.dev3.dist-info/METADATA
odoo11_addon_product_variant_specific_tax-11.0.1.0.0.99.dev3.dist-info/WHEEL
odoo11_addon_product_variant_specific_tax-11.0.1.0.0.99.dev3.dist-info/top_level.txt
odoo11_addon_product_variant_specific_tax-11.0.1.0.0.99.dev3.dist-info/RECORD
